GUI_pygameLIB/Ver.py
GUI_pygameLIB/__init__.py
GUI_pygameLIB-0.0.22.dist-info/METADATA
GUI_pygameLIB-0.0.22.dist-info/WHEEL
GUI_pygameLIB-0.0.22.dist-info/top_level.txt
GUI_pygameLIB-0.0.22.dist-info/RECORD
