Metadata-Version: 2.1
Name: GUI_pygameLIB
Version: 0.0.22
Summary: A python library for creating simple GUI with pygame.
Author: Back
License: GPL-3.0-or-later
Classifier: Programming Language :: Python :: 3
Classifier: License :: OSI Approved :: GNU General Public License v3 or later (GPLv3+)
Classifier: Operating System :: OS Independent
Requires-Python: >=3.6
Requires-Dist: pygame
